bookmarks/__init__.py
bookmarks/apps.py
bookmarks/docs/allauth.md
bookmarks/docs/configure.md
bookmarks/docs/frontend.md
bookmarks/docs/setup.md
bookmarks/managers.py
bookmarks/migrations/0001_initial.py
bookmarks/migrations/0002_initial.py
bookmarks/migrations/__init__.py
bookmarks/models.py
bookmarks/static/css/modal.css
bookmarks/static/css/starter.css
bookmarks/static/css/throbber.css
bookmarks/static/img/favicons/android-chrome-192x192.png
bookmarks/static/img/favicons/android-chrome-512x512.png
bookmarks/static/img/favicons/apple-touch-icon.png
bookmarks/static/img/favicons/favicon-16x16.png
bookmarks/static/img/favicons/favicon-32x32.png
bookmarks/static/img/favicons/favicon.ico
bookmarks/static/img/favicons/site.webmanifest
bookmarks/templates/bookmarks/bookmark_list.html
bookmarks/templates/bookmarks/items_to_load.html
bookmarks/templates/commons/_badge.html
bookmarks/templates/commons/_panel.html
bookmarks/templates/commons/_tag_form.html
bookmarks/templates/commons/_toggle_bookmark_status.html
bookmarks/templates/commons/_toggle_form.html
bookmarks/templates/commons/modal.html
bookmarks/templates/tags/filter_objects_by_tag_model.html
bookmarks/templates/tags/tag_list.html
bookmarks/templates/tags/tag_list_annotated_model.html
bookmarks/templates/tags/tag_list_annotated_model_list.html
bookmarks/templatetags/__init__.py
bookmarks/templatetags/bookmark_util.py
bookmarks/urls.py
bookmarks/utils.py
bookmarks/views.py
examples/__init__.py
examples/admin.py
examples/apps.py
examples/fixtures/res.yaml
examples/migrations/0001_initial.py
examples/migrations/0002_initial.py
examples/migrations/__init__.py
examples/models.py
examples/urls.py
examples/views.py
django_yabl-0.2.0.dist-info/WHEEL
django_yabl-0.2.0.dist-info/METADATA
django_yabl-0.2.0.dist-info/RECORD
