Metadata-Version: 2.1
Name: django-yabl
Version: 0.2.0
Summary: Yet another bookmarking library (yabl) for Django. Bookmark and tag arbitrary models.
Home-page: https://github.com/justmars/django-yabl
License: MIT
Author: Marcelino G. Veloso III
Author-email: mars@veloso.one
Requires-Python: >=3.8,<4.0
Classifier: License :: OSI Approved :: MIT License
Classifier: Programming Language :: Python :: 3
Classifier: Programming Language :: Python :: 3.8
Classifier: Programming Language :: Python :: 3.9
Classifier: Programming Language :: Python :: 3.10
Requires-Dist: Django (>=4.0,<5.0)
Requires-Dist: django-debug-toolbar (>=3.2,<4.0)
Requires-Dist: django-extensions (>=3.1,<4.0)
Project-URL: Repository, https://github.com/justmars/django-yabl
